hanz/__init__.py
hanz/hanz.py
hanz-0.1.5.dist-info/LICENSE
hanz-0.1.5.dist-info/METADATA
hanz-0.1.5.dist-info/WHEEL
hanz-0.1.5.dist-info/top_level.txt
hanz-0.1.5.dist-info/RECORD
